kboxx/__init__.py
kboxx/transformer/__init__.py
kboxx/transformer/config.py
kboxx/transformer/layers/__init__.py
kboxx/transformer/layers/layers.py
kboxx/transformer/models/__init__.py
kboxx/transformer/models/models.py
kboxx/transformer/utils/__init__.py
kboxx/transformer/utils/utils.py
kboxx/utils/__init__.py
kboxx/utils/tokenize.py
kboxx/vit/__init__.py
kboxx/vit/config.py
kboxx/vit/layers/__init__.py
kboxx/vit/layers/layers.py
kboxx/vit/models/__init__.py
kboxx/vit/models/models.py
kboxx/vit/utils/__init__.py
kboxx/vit/utils/utils.py
kboxx-1.0.3.dist-info/LICENSE.txt
kboxx-1.0.3.dist-info/METADATA
kboxx-1.0.3.dist-info/WHEEL
kboxx-1.0.3.dist-info/top_level.txt
kboxx-1.0.3.dist-info/RECORD
